omega_agents/__init__.py
omega_agents-0.2.4.dist-info/METADATA
omega_agents-0.2.4.dist-info/WHEEL
omega_agents-0.2.4.dist-info/entry_points.txt
omega_agents-0.2.4.dist-info/RECORD
