Metadata-Version: 2.4
Name: omega_agents
Version: 0.2.4
Summary: OmegaAgents is a scalable ReAct-based multi-agent framework designed for rapid solution development. It enables LLMs and agents to dynamically create and coordinate sub-agents during inference, mimicking human-like task distribution and collaboration. With built-in tools, parallel processing, and ephemeral memory management, it streamlines complex problem-solving through autonomous agent orchestration and structured output validation.
Author-email: Arpit Sharma <arpitsh018@gmail.com>
License-Expression: MIT
Requires-Python: >=3.9
Requires-Dist: aiohttp
Requires-Dist: google-search-results>=2.4.2
Requires-Dist: jsonschema
Requires-Dist: openai
Requires-Dist: pydantic-settings>=2.0.0
Requires-Dist: pydantic>=1.10
Requires-Dist: requests>=2.28
Provides-Extra: test
Requires-Dist: pytest-cov>=3.0; extra == 'test'
Requires-Dist: pytest>=7.0; extra == 'test'
